Metadata-Version: 2.1
Name: catbench
Version: 1.0.0
Summary: CatBench: Benchmark Framework of Machine Learning Interatomic Potentials for Adsorption Energy Predictions in Heterogeneous Catalysis
Home-page: https://github.com/JinukMoon/catbench
Author: JinukMoon
Author-email: jumoon@snu.ac.kr
License: MIT
Keywords: MLIP benchmark for catalysis
Classifier: Programming Language :: Python :: 3.8
Classifier: Programming Language :: Python :: 3.9
Classifier: Programming Language :: Python :: 3.10
Classifier: Programming Language :: Python :: 3.11
Classifier: License :: OSI Approved :: MIT License
Requires-Python: >=3.8
License-File: LICENSE
Requires-Dist: ase>=3.22.1
Requires-Dist: numpy>=1.20.0
Requires-Dist: pandas>=1.3.0
Requires-Dist: matplotlib>=3.4.0
Requires-Dist: requests>=2.25.0
Requires-Dist: xlsxwriter>=3.2.0
Requires-Dist: pyyaml>=5.4.0
Requires-Dist: scipy>=1.7.0
Provides-Extra: d3
Requires-Dist: torch>=1.12.0; extra == "d3"
